config.create.example.yaml
config.edit.example.yaml
environment.yaml
nfdata/__init__.py
nfdata/_errors.py
nfdata/_utility.py
nfdata/compiler.py
nfdata/console.py
nfdata/land_use.default.yaml
nfdata/model_vars.yaml
nfdata/routing.py
nfdata-0.3.0.dist-info/LICENSE
nfdata-0.3.0.dist-info/METADATA
nfdata-0.3.0.dist-info/WHEEL
nfdata-0.3.0.dist-info/entry_points.txt
nfdata-0.3.0.dist-info/RECORD
