Metadata-Version: 2.3
Name: nfdata
Version: 0.3.0
Summary: Compile and edit input data for the NanoFASE model
License: BSD-3-Clause
Author: Sam Harrison
Author-email: samharrison.xg@gmail.com
Requires-Python: >=3.10,<4.0
Classifier: License :: OSI Approved :: BSD License
Classifier: Programming Language :: Python :: 3
Classifier: Programming Language :: Python :: 3.10
Classifier: Programming Language :: Python :: 3.11
Classifier: Programming Language :: Python :: 3.12
Classifier: Programming Language :: Python :: 3.13
Requires-Dist: Pint (>=0.24.1,<0.25.0)
Requires-Dist: f90nml (>=1.4.4,<2.0.0)
Requires-Dist: geopandas (>=1.0.0,<2.0.0)
Requires-Dist: netcdf4 (>=1.7.1.post1,<2.0.0)
Requires-Dist: numpy (>=2.0.0,<3.0.0)
Requires-Dist: pandas (>=2.2.2,<3.0.0)
Requires-Dist: pytest (>=8.3.5,<9.0.0)
Requires-Dist: rasterio (>=1.3.10,<2.0.0)
Requires-Dist: ruamel.yaml (>=0.18.6,<0.19.0)
Requires-Dist: shapely (>=2.0.4,<3.0.0)
Requires-Dist: whitebox (>=2.3.6,<3.0.0)
Project-URL: Documentation, https://nerc-ceh.github.io/nanofase
